<?xml version="1.0" encoding="UTF-8" ?>
<!DOCTYPE struts PUBLIC "-//Apache Software Foundation//DTD Struts Configuration 2.1//EN" "http://struts.apache.org/dtds/struts-2.1.dtd">
<struts>
	<constant name="struts.i18n.encoding" value="UTF-8"></constant>
	
	<include file="struts-default.xml" />

	<!--系统管理员可以做的操作，受权限控制的Action请求配置-->
	<package name="store_manager" extends="json-default">
		<interceptors>
			<!--定义一个拦截器-->
			<interceptor class="admin.ru.own.www.logic.AdminAuthorityInterceptor" name="sessionNull">
			</interceptor>
			<!--定义一个包含权限检查的拦截器栈-->
			<interceptor-stack name="mydefault">
				<interceptor-ref name="defaultStack" />
				<!--配置自定义的拦截器-->
				<interceptor-ref name="sessionNull" />
			</interceptor-stack>
		</interceptors>
		<default-interceptor-ref name="mydefault" />
		<!--定义全局Result-->
		<global-results>
			<result name="login" type="redirect">/admin_relogin.jsp</result>
		</global-results>
		
		
		
		
        
        <!-- 商店页脚信息管理  -->
        <action name="setStoreFooter" class="admin.ru.own.www.logic.StoreOperate" method="setStoreFooterInfo">
            <result name="success" type="json" >  
             
            </result>
        </action>
        
        <action name="getStoreFooter" class="admin.ru.own.www.logic.StoreOperate" method="getStoreFooterInfo">
            <result name="success" type="json" >  
             	<param name="root">info</param>
            </result>
        </action>
        
        <!-- 商店首页显示信息管理  -->
        <action name="getAllHomeInfo" class="admin.ru.own.www.logic.StoreOperate" method="getAllHomeInfo">
            <result name="success" type="json" >  
             <param name="root">storeFooterInfoList</param>
            </result>
        </action>
        
        <action name="storeHomeInfo_insert" class="admin.ru.own.www.logic.StoreOperate" method="InsertStoreHomeInfo">
            <result name="success" type="json" >  
             <param name="root">sftInfo</param>
            </result>
        </action>
        
        <action name="storeHomeInfo_delete" class="admin.ru.own.www.logic.StoreOperate" method="deleteStoreHomeInfo">
            <result name="success" type="json" >  
             <!-- <param name="root">Users</param> -->
	              <!-- <param name="excludeProperties"></param> -->
	              <param name = "includeProperties"></param > 
	              <param name="excludeNullProperties" >true</param>
            </result>
        </action>
        
        <action name="storeHomeInfo_fecth" class="admin.ru.own.www.logic.StoreOperate" method="fetchStoreHomeInfoById">
            <result name="success" type="json" >  
             <!-- <param name="root">Users</param> -->
	              <!-- <param name="excludeProperties"></param> -->
	              <param name = "includeProperties"></param > 
	              <param name="excludeNullProperties" >false</param>
            </result>
        </action>
        
        <action name="modify_basic_info" class="admin.ru.own.www.logic.StoreOperate" method="modify_basic_info">
            <result name="success" type="json" >  
             	<!-- <param name="root">Users</param> -->
	              <!-- <param name="excludeProperties"></param> -->
	              <param name = "includeProperties"></param > 
	              <param name="excludeNullProperties" >false</param>
            </result>
        </action>
        
        <action name="modify_xiangxi_info" class="admin.ru.own.www.logic.StoreOperate" method="modify_xiangxi_info">
            <result name="success" type="json" >  
             	<!-- <param name="root">Users</param> -->
	              <!-- <param name="excludeProperties"></param> -->
	              <param name = "includeProperties"></param > 
	              <param name="excludeNullProperties" >false</param>
            </result>
        </action>
        
                
        <action name="modify_xiangxi_content" class="admin.ru.own.www.logic.StoreOperate" method="modify_xiangxi_content">
            <result name="success" type="json" >  
             	<!-- <param name="root">Users</param> -->
	              <!-- <param name="excludeProperties"></param> -->
	              <param name = "includeProperties"></param > 
	              <param name="excludeNullProperties" >false</param>
            </result>
        </action>
        
        
        <action name="editStoreHomeXiangXiInfo" class="admin.ru.own.www.logic.StoreOperate" method="fetchStoreHomeInfoById">
            <result name="success" > /jqladmin/storemange/editsotrehomexiangxiinfo.jsp  </result>
        </action>
        
        
        
        
        

	</package>

</struts>    
